README.txt
setup.py
pyClamd.egg-info/PKG-INFO
pyClamd.egg-info/SOURCES.txt
pyClamd.egg-info/dependency_links.txt
pyClamd.egg-info/top_level.txt
pyclamd/__init__.py
pyclamd/pyclamd.py
pyclamd/test_pyclamd.py